mplb_tools_36/__init__.py
mplb_tools_36/axes.py
mplb_tools_36/config.py
mplb_tools_36/in_out.py
mplb_tools_36/main.py
mplb_tools_36/version.py
mplb_tools_36/test/axes_decorations.py
mplb_tools_36/test/simple_display.py
mplb_tools_36/type/axes.py
mplb_tools_36/type/base.py
mplb_tools_36/type/colorbar.py
mplb_tools_36/type/slider.py
mplb_tools_36-2023.1.dist-info/METADATA
mplb_tools_36-2023.1.dist-info/WHEEL
mplb_tools_36-2023.1.dist-info/top_level.txt
mplb_tools_36-2023.1.dist-info/RECORD
