Metadata-Version: 2.1
Name: mplb-tools-36
Version: 2023.1
Summary: A Toolbox for Matplotlib
Home-page: https://src.koda.cnrs.fr/eric.debreuve/mplb-tools-36/
Author: Eric Debreuve
Author-email: eric.debreuve@cnrs.fr
License: CeCILL-2.1
Project-URL: Documentation, https://src.koda.cnrs.fr/eric.debreuve/mplb-tools-36//-/wikis/home
Project-URL: Source, https://src.koda.cnrs.fr/eric.debreuve/mplb-tools-36/
Keywords: matplotlib,image,toolbox,tools
Classifier: Topic :: Scientific/Engineering :: Image Recognition
Classifier: Intended Audience :: Science/Research
Classifier: License :: OSI Approved :: CEA CNRS Inria Logiciel Libre License, version 2.1 (CeCILL-2.1)
Classifier: Programming Language :: Python :: 3.10
Classifier: Development Status :: 4 - Beta
Requires-Python: >=3.10
